mdiocre/__init__.py
mdiocre/__meta__.py
mdiocre/core.py
mdiocre/utils.py
mdiocre/wizard.py
mdiocre/interface/cli.py
mdiocre/interface/gui.py
mdiocre/parsers/__init__.py
mdiocre/parsers/gem.py
mdiocre/parsers/html.py
mdiocre/parsers/markdown.py
mdiocre/parsers/rst.py
mdiocre/parsers/zim.py
mdiocre-3.5.3.dist-info/LICENSE
mdiocre-3.5.3.dist-info/METADATA
mdiocre-3.5.3.dist-info/WHEEL
mdiocre-3.5.3.dist-info/entry_points.txt
mdiocre-3.5.3.dist-info/top_level.txt
mdiocre-3.5.3.dist-info/RECORD
