Metadata-Version: 2.1
Name: mdiocre
Version: 3.5.3
Summary: Static website generator
Home-page: https://zumi.neocities.org/stuff/mdiocre
Author: Zumi Daxuya
Author-email: daxuya.zumi+mdiocre@protonmail.com
License: MIT
Keywords: converter,generator,markdown,html,static
Classifier: Development Status :: 4 - Beta
Classifier: Intended Audience :: Developers
Classifier: License :: OSI Approved :: MIT License
Classifier: Operating System :: OS Independent
Classifier: Natural Language :: English
Classifier: Programming Language :: Python
Classifier: Programming Language :: Python :: 3
Classifier: Programming Language :: Python :: 3.8
Classifier: Programming Language :: Python :: 3.9
Classifier: Topic :: Software Development :: Libraries :: Python Modules
License-File: LICENSE
Requires-Dist: markdown
Requires-Dist: py-gfm
